test_panda_pypi/__about__.py
test_panda_pypi/__init__.py
test_panda_pypi/app.py
test_panda_pypi-0.1.2.dist-info/METADATA
test_panda_pypi-0.1.2.dist-info/WHEEL
test_panda_pypi-0.1.2.dist-info/entry_points.txt
test_panda_pypi-0.1.2.dist-info/licenses/LICENSE
test_panda_pypi-0.1.2.dist-info/RECORD
